{"namespace":"WantedDesignSystem_019dde","components":[],"startingPoints":[],"cards":[{"path":"preview/iconography.html","group":"Brand","viewport":"700x140","subtitle":"Lucide stand-in — 24px, 1.5–2px stroke, rounded caps","name":"Iconography"},{"path":"preview/logos.html","group":"Brand","viewport":"700x160","subtitle":"Wanted family wordmarks — symbol, sub-brand variants","name":"Logos"},{"path":"preview/principles.html","group":"Brand","viewport":"700x160","subtitle":"Calm · Bilingual · Flat · One blue","name":"Brand principles"},{"path":"preview/colors-coolneutral.html","group":"Colors","viewport":"700x160","subtitle":"The grayscale spine — every gray in the system","name":"Colors — Cool Neutral spine"},{"path":"preview/colors-primary.html","group":"Colors","viewport":"700x180","subtitle":"Brand blue scale — #0066FF is the only true brand color","name":"Colors — Primary blue"},{"path":"preview/colors-semantic-dark.html","group":"Colors","viewport":"700x220","subtitle":"Semantic tokens for the dark theme","name":"Colors — Semantic (dark)"},{"path":"preview/colors-semantic-light.html","group":"Colors","viewport":"700x220","subtitle":"Semantic tokens for the light theme","name":"Colors — Semantic (light)"},{"path":"preview/colors-status.html","group":"Colors","viewport":"700x160","subtitle":"Positive / Cautionary / Negative + Gigs accent","name":"Colors — Status & accents"},{"path":"preview/buttons.html","group":"Components","viewport":"700x200","subtitle":"Primary / Solid / Outline / Tonal / Text — three sizes","name":"Buttons"},{"path":"preview/inputs.html","group":"Components","viewport":"700x280","subtitle":"Text fields, focus ring, search input, pill tags","name":"Inputs & chips"},{"path":"preview/job-card.html","group":"Components","viewport":"700x180","subtitle":"The signature listing pattern — company · title · meta · tags","name":"Job card"},{"path":"preview/list-row.html","group":"Components","viewport":"700x240","subtitle":"Settings-style rows with icon, title, meta, trailing affordance","name":"List rows"},{"path":"preview/radii.html","group":"Spacing","viewport":"700x160","subtitle":"4–32px + pill + circle — defaults to 8–16 for chrome","name":"Radii scale"},{"path":"preview/shadows.html","group":"Spacing","viewport":"700x180","subtitle":"5-step elevation, two-shadow stacks, near-black tint","name":"Shadows / elevation"},{"path":"preview/spacing-scale.html","group":"Spacing","viewport":"700x160","subtitle":"4-pt grid — 4·8·12·16·20·24·32·48·64","name":"Spacing scale"},{"path":"preview/type-body.html","group":"Type","viewport":"700x220","subtitle":"Pretendard JP — Title / Heading / Body / Caption","name":"Type — Body & UI"},{"path":"preview/type-display.html","group":"Type","viewport":"700x220","subtitle":"Wanted Sans display face — hero, wordmark, decorative numerals","name":"Type — Display"},{"path":"preview/type-scale.html","group":"Type","viewport":"700x320","subtitle":"Sizes, weights, line-heights, tracking — by role","name":"Type — Scale table"},{"path":"ui_kits/wanted/index.html","group":"UI Kit — Wanted","viewport":"1280x900","subtitle":"Click-thru prototype — Home / Jobs / Bookmarks / Profile","name":"Wanted UI kit"}],"globalCssPaths":["colors_and_type.css","preview/_card.css"],"tokens":[{"name":"--w-common-100","value":"#ffffff","kind":"color","definedIn":"colors_and_type.css"},{"name":"--w-common-99","value":"#f7f7f7","kind":"color","definedIn":"colors_and_type.css"},{"name":"--w-common-95","value":"#dcdcdc","kind":"color","definedIn":"colors_and_type.css"},{"name":"--w-common-90","value":"#c4c4c4","kind":"color","definedIn":"colors_and_type.css"},{"name":"--w-common-80","value":"#b0b0b0","kind":"color","definedIn":"colors_and_type.css"},{"name":"--w-common-70","value":"#9b9b9b","kind":"color","definedIn":"colors_and_type.css"},{"name":"--w-common-60","value":"#8a8a8a","kind":"color","definedIn":"colors_and_type.css"},{"name":"--w-common-50","value":"#737373","kind":"color","definedIn":"colors_and_type.css"},{"name":"--w-common-40","value":"#5c5c5c","kind":"color","definedIn":"colors_and_type.css"},{"name":"--w-common-30","value":"#474747","kind":"color","definedIn":"colors_and_type.css"},{"name":"--w-common-20","value":"#303030","kind":"color","definedIn":"colors_and_type.css"},{"name":"--w-common-15","value":"#2a2a2a","kind":"color","definedIn":"colors_and_type.css"},{"name":"--w-common-10","value":"#1c1c1c","kind":"color","definedIn":"colors_and_type.css"},{"name":"--w-common-5","value":"#171717","kind":"color","definedIn":"colors_and_type.css"},{"name":"--w-common-3","value":"#0f0f0f","kind":"color","definedIn":"colors_and_type.css"},{"name":"--w-common-0","value":"#000000","kind":"color","definedIn":"colors_and_type.css"},{"name":"--w-coolneutral-99","value":"#f7f7f8","kind":"color","definedIn":"colors_and_type.css"},{"name":"--w-coolneutral-98","value":"#f4f4f5","kind":"color","definedIn":"colors_and_type.css"},{"name":"--w-coolneutral-95","value":"#eaebec","kind":"color","definedIn":"colors_and_type.css"},{"name":"--w-coolneutral-90","value":"#e1e2e4","kind":"color","definedIn":"colors_and_type.css"},{"name":"--w-coolneutral-85","value":"#dbdcdf","kind":"color","definedIn":"colors_and_type.css"},{"name":"--w-coolneutral-80","value":"#c2c4c8","kind":"color","definedIn":"colors_and_type.css"},{"name":"--w-coolneutral-70","value":"#aeb0b6","kind":"color","definedIn":"colors_and_type.css"},{"name":"--w-coolneutral-60","value":"#989ba2","kind":"color","definedIn":"colors_and_type.css"},{"name":"--w-coolneutral-55","value":"#878a93","kind":"color","definedIn":"colors_and_type.css"},{"name":"--w-coolneutral-50","value":"#70737c","kind":"color","definedIn":"colors_and_type.css"},{"name":"--w-coolneutral-40","value":"#5a5c63","kind":"color","definedIn":"colors_and_type.css"},{"name":"--w-coolneutral-35","value":"#46474c","kind":"color","definedIn":"colors_and_type.css"},{"name":"--w-coolneutral-30","value":"#37383c","kind":"color","definedIn":"colors_and_type.css"},{"name":"--w-coolneutral-28","value":"#333438","kind":"color","definedIn":"colors_and_type.css"},{"name":"--w-coolneutral-25","value":"#2e2f33","kind":"color","definedIn":"colors_and_type.css"},{"name":"--w-coolneutral-20","value":"#292a2d","kind":"color","definedIn":"colors_and_type.css"},{"name":"--w-coolneutral-15","value":"#212225","kind":"color","definedIn":"colors_and_type.css"},{"name":"--w-coolneutral-10","value":"#1b1c1e","kind":"color","definedIn":"colors_and_type.css"},{"name":"--w-coolneutral-5","value":"#171719","kind":"color","definedIn":"colors_and_type.css"},{"name":"--w-coolneutral-3","value":"#141415","kind":"color","definedIn":"colors_and_type.css"},{"name":"--w-coolneutral-1","value":"#0f0f10","kind":"color","definedIn":"colors_and_type.css"},{"name":"--w-blue-99","value":"#f7fbff","kind":"color","definedIn":"colors_and_type.css"},{"name":"--w-blue-95","value":"#eaf2fe","kind":"color","definedIn":"colors_and_type.css"},{"name":"--w-blue-90","value":"#c9defe","kind":"color","definedIn":"colors_and_type.css"},{"name":"--w-blue-80","value":"#9ec5ff","kind":"color","definedIn":"colors_and_type.css"},{"name":"--w-blue-70","value":"#69a5ff","kind":"color","definedIn":"colors_and_type.css"},{"name":"--w-blue-65","value":"#4f95ff","kind":"color","definedIn":"colors_and_type.css"},{"name":"--w-blue-60","value":"#3385ff","kind":"color","definedIn":"colors_and_type.css"},{"name":"--w-blue-55","value":"#1a75ff","kind":"color","definedIn":"colors_and_type.css"},{"name":"--w-blue-50","value":"#0066ff","kind":"color","definedIn":"colors_and_type.css"},{"name":"--w-blue-45","value":"#005eeb","kind":"color","definedIn":"colors_and_type.css"},{"name":"--w-blue-40","value":"#0054d1","kind":"color","definedIn":"colors_and_type.css"},{"name":"--w-blue-30","value":"#003e9c","kind":"color","definedIn":"colors_and_type.css"},{"name":"--w-blue-20","value":"#002966","kind":"color","definedIn":"colors_and_type.css"},{"name":"--w-blue-10","value":"#001536","kind":"color","definedIn":"colors_and_type.css"},{"name":"--w-red-99","value":"#fffafa","kind":"color","definedIn":"colors_and_type.css"},{"name":"--w-red-95","value":"#feecec","kind":"color","definedIn":"colors_and_type.css"},{"name":"--w-red-90","value":"#fed5d5","kind":"color","definedIn":"colors_and_type.css"},{"name":"--w-red-80","value":"#ffb5b5","kind":"color","definedIn":"colors_and_type.css"},{"name":"--w-red-70","value":"#ff8c8c","kind":"color","definedIn":"colors_and_type.css"},{"name":"--w-red-60","value":"#ff6363","kind":"color","definedIn":"colors_and_type.css"},{"name":"--w-red-50","value":"#ff4242","kind":"color","definedIn":"colors_and_type.css"},{"name":"--w-red-45","value":"#e52222","kind":"color","definedIn":"colors_and_type.css"},{"name":"--w-red-30","value":"#b20c0c","kind":"color","definedIn":"colors_and_type.css"},{"name":"--w-red-20","value":"#750404","kind":"color","definedIn":"colors_and_type.css"},{"name":"--w-red-10","value":"#3b0101","kind":"color","definedIn":"colors_and_type.css"},{"name":"--w-green-99","value":"#f2fff6","kind":"color","definedIn":"colors_and_type.css"},{"name":"--w-green-95","value":"#d9ffe6","kind":"color","definedIn":"colors_and_type.css"},{"name":"--w-green-90","value":"#acfcc7","kind":"color","definedIn":"colors_and_type.css"},{"name":"--w-green-80","value":"#7df5a5","kind":"color","definedIn":"colors_and_type.css"},{"name":"--w-green-70","value":"#49e57d","kind":"color","definedIn":"colors_and_type.css"},{"name":"--w-green-60","value":"#1ed45a","kind":"color","definedIn":"colors_and_type.css"},{"name":"--w-green-50","value":"#00bf40","kind":"color","definedIn":"colors_and_type.css"},{"name":"--w-green-40","value":"#009632","kind":"color","definedIn":"colors_and_type.css"},{"name":"--w-green-30","value":"#006e25","kind":"color","definedIn":"colors_and_type.css"},{"name":"--w-green-20","value":"#004517","kind":"color","definedIn":"colors_and_type.css"},{"name":"--w-green-10","value":"#00240c","kind":"color","definedIn":"colors_and_type.css"},{"name":"--w-yellow-99","value":"#fffcf7","kind":"color","definedIn":"colors_and_type.css"},{"name":"--w-yellow-95","value":"#fef4e6","kind":"color","definedIn":"colors_and_type.css"},{"name":"--w-yellow-90","value":"#fee6c6","kind":"color","definedIn":"colors_and_type.css"},{"name":"--w-yellow-80","value":"#ffd49c","kind":"color","definedIn":"colors_and_type.css"},{"name":"--w-yellow-70","value":"#ffc06e","kind":"color","definedIn":"colors_and_type.css"},{"name":"--w-yellow-60","value":"#ffa938","kind":"color","definedIn":"colors_and_type.css"},{"name":"--w-yellow-50","value":"#ff9200","kind":"color","definedIn":"colors_and_type.css"},{"name":"--w-yellow-45","value":"#d47800","kind":"color","definedIn":"colors_and_type.css"},{"name":"--w-yellow-30","value":"#9c5800","kind":"color","definedIn":"colors_and_type.css"},{"name":"--w-yellow-20","value":"#663a00","kind":"color","definedIn":"colors_and_type.css"},{"name":"--w-yellow-10","value":"#361e00","kind":"color","definedIn":"colors_and_type.css"},{"name":"--w-redorange-99","value":"#fffaf7","kind":"color","definedIn":"colors_and_type.css"},{"name":"--w-redorange-95","value":"#feeee5","kind":"color","definedIn":"colors_and_type.css"},{"name":"--w-redorange-90","value":"#fedbc6","kind":"color","definedIn":"colors_and_type.css"},{"name":"--w-redorange-80","value":"#ffc09c","kind":"color","definedIn":"colors_and_type.css"},{"name":"--w-redorange-70","value":"#ff9c63","kind":"color","definedIn":"colors_and_type.css"},{"name":"--w-redorange-60","value":"#ff7b2e","kind":"color","definedIn":"colors_and_type.css"},{"name":"--w-redorange-50","value":"#ff5e00","kind":"color","definedIn":"colors_and_type.css"},{"name":"--w-redorange-45","value":"#f55a00","kind":"color","definedIn":"colors_and_type.css"},{"name":"--w-redorange-40","value":"#cc4b00","kind":"color","definedIn":"colors_and_type.css"},{"name":"--w-redorange-30","value":"#943600","kind":"color","definedIn":"colors_and_type.css"},{"name":"--w-redorange-20","value":"#5c2200","kind":"color","definedIn":"colors_and_type.css"},{"name":"--w-redorange-10","value":"#2e1100","kind":"color","definedIn":"colors_and_type.css"},{"name":"--w-lime-50","value":"#58cf04","kind":"color","definedIn":"colors_and_type.css"},{"name":"--w-lime-60","value":"#6be016","kind":"color","definedIn":"colors_and_type.css"},{"name":"--w-lime-70","value":"#88f03e","kind":"color","definedIn":"colors_and_type.css"},{"name":"--w-cyan-50","value":"#00bdde","kind":"color","definedIn":"colors_and_type.css"},{"name":"--w-cyan-60","value":"#28d0ed","kind":"color","definedIn":"colors_and_type.css"},{"name":"--w-cobalt-50","value":"#00aeff","kind":"color","definedIn":"colors_and_type.css"},{"name":"--w-cobalt-60","value":"#3dc2ff","kind":"color","definedIn":"colors_and_type.css"},{"name":"--w-purple-50","value":"#6541f2","kind":"color","definedIn":"colors_and_type.css"},{"name":"--w-purple-60","value":"#7d5ef7","kind":"color","definedIn":"colors_and_type.css"},{"name":"--w-purple-70","value":"#9e86fc","kind":"color","definedIn":"colors_and_type.css"},{"name":"--color-primary-normal","value":"var(--w-blue-50)","kind":"color","definedIn":"colors_and_type.css"},{"name":"--color-primary-strong","value":"var(--w-blue-45)","kind":"color","definedIn":"colors_and_type.css"},{"name":"--color-primary-heavy","value":"var(--w-blue-40)","kind":"color","definedIn":"colors_and_type.css"},{"name":"--color-label-normal","value":"rgba(23, 23, 25, 1)","kind":"color","definedIn":"colors_and_type.css"},{"name":"--color-label-strong","value":"rgba(0, 0, 0, 1)","kind":"color","definedIn":"colors_and_type.css"},{"name":"--color-label-neutral","value":"rgba(46, 47, 51, 0.88)","kind":"color","definedIn":"colors_and_type.css"},{"name":"--color-label-alternative","value":"rgba(46, 47, 51, 0.61)","kind":"color","definedIn":"colors_and_type.css"},{"name":"--color-label-assistive","value":"rgba(46, 47, 51, 0.28)","kind":"color","definedIn":"colors_and_type.css"},{"name":"--color-label-disable","value":"rgba(46, 47, 51, 0.16)","kind":"color","definedIn":"colors_and_type.css"},{"name":"--color-label-inverse","value":"#ffffff","kind":"color","definedIn":"colors_and_type.css"},{"name":"--color-static-white","value":"#ffffff","kind":"color","definedIn":"colors_and_type.css"},{"name":"--color-static-black","value":"#000000","kind":"color","definedIn":"colors_and_type.css"},{"name":"--color-background-normal","value":"#ffffff","kind":"color","definedIn":"colors_and_type.css"},{"name":"--color-background-alternative","value":"#f7f7f8","kind":"color","definedIn":"colors_and_type.css"},{"name":"--color-background-elevated","value":"#ffffff","kind":"color","definedIn":"colors_and_type.css"},{"name":"--color-background-elevated-alt","value":"#fafafa","kind":"color","definedIn":"colors_and_type.css"},{"name":"--color-background-inverse","value":"#171719","kind":"color","definedIn":"colors_and_type.css"},{"name":"--color-line-normal","value":"rgba(112, 115, 124, 0.22)","kind":"color","definedIn":"colors_and_type.css"},{"name":"--color-line-neutral","value":"rgba(112, 115, 124, 0.16)","kind":"color","definedIn":"colors_and_type.css"},{"name":"--color-line-alternative","value":"rgba(112, 115, 124, 0.08)","kind":"color","definedIn":"colors_and_type.css"},{"name":"--color-line-strong","value":"rgba(112, 115, 124, 0.40)","kind":"color","definedIn":"colors_and_type.css"},{"name":"--color-status-positive","value":"var(--w-green-50)","kind":"color","definedIn":"colors_and_type.css"},{"name":"--color-status-cautionary","value":"var(--w-yellow-50)","kind":"color","definedIn":"colors_and_type.css"},{"name":"--color-status-negative","value":"#ff4242","kind":"color","definedIn":"colors_and_type.css"},{"name":"--color-accent-redorange","value":"var(--w-redorange-50)","kind":"color","definedIn":"colors_and_type.css"},{"name":"--color-accent-yellow","value":"var(--w-yellow-50)","kind":"color","definedIn":"colors_and_type.css"},{"name":"--color-accent-violet","value":"var(--w-purple-50)","kind":"color","definedIn":"colors_and_type.css"},{"name":"--color-inverse-primary","value":"#3385ff","kind":"color","definedIn":"colors_and_type.css"},{"name":"--color-fill-normal","value":"rgba(112, 115, 124, 0.08)","kind":"color","definedIn":"colors_and_type.css"},{"name":"--color-fill-strong","value":"rgba(112, 115, 124, 0.16)","kind":"color","definedIn":"colors_and_type.css"},{"name":"--color-fill-neutral","value":"rgba(112, 115, 124, 0.05)","kind":"color","definedIn":"colors_and_type.css"},{"name":"--color-interaction-inactive","value":"rgba(46, 47, 51, 0.28)","kind":"color","definedIn":"colors_and_type.css"},{"name":"--color-interaction-disable","value":"rgba(112, 115, 124, 0.22)","kind":"color","definedIn":"colors_and_type.css"},{"name":"--color-interaction-hover","value":"rgba(0, 0, 0, 0.04)","kind":"color","definedIn":"colors_and_type.css"},{"name":"--color-interaction-pressed","value":"rgba(0, 0, 0, 0.08)","kind":"color","definedIn":"colors_and_type.css"},{"name":"--shadow-emphasize-xsmall","value":"0px 1px 2px -1px rgba(23, 23, 23, 0.10)","kind":"shadow","definedIn":"colors_and_type.css"},{"name":"--shadow-emphasize-small","value":"0px 1px 2px 0px  rgba(23, 23, 23, 0.07), 0px 1px 3px 0px rgba(23,23,23,0.10)","kind":"shadow","definedIn":"colors_and_type.css"},{"name":"--shadow-emphasize-medium","value":"0px 1px 4px -1px rgba(23, 23, 23, 0.07), 0px 4px 8px 0px rgba(23,23,23,0.10)","kind":"shadow","definedIn":"colors_and_type.css"},{"name":"--shadow-emphasize-large","value":"0px 4px 8px -2px rgba(23, 23, 23, 0.10), 0px 12px 24px 0px rgba(23,23,23,0.12)","kind":"shadow","definedIn":"colors_and_type.css"},{"name":"--shadow-emphasize-xlarge","value":"0px 8px 16px -4px rgba(23,23,23,0.10), 0px 24px 48px 0px rgba(23,23,23,0.12)","kind":"shadow","definedIn":"colors_and_type.css"},{"name":"--space-1","value":"4px","kind":"spacing","definedIn":"colors_and_type.css"},{"name":"--space-2","value":"8px","kind":"spacing","definedIn":"colors_and_type.css"},{"name":"--space-3","value":"12px","kind":"spacing","definedIn":"colors_and_type.css"},{"name":"--space-4","value":"16px","kind":"spacing","definedIn":"colors_and_type.css"},{"name":"--space-5","value":"20px","kind":"spacing","definedIn":"colors_and_type.css"},{"name":"--space-6","value":"24px","kind":"spacing","definedIn":"colors_and_type.css"},{"name":"--space-8","value":"32px","kind":"spacing","definedIn":"colors_and_type.css"},{"name":"--space-10","value":"40px","kind":"spacing","definedIn":"colors_and_type.css"},{"name":"--space-12","value":"48px","kind":"spacing","definedIn":"colors_and_type.css"},{"name":"--space-16","value":"64px","kind":"spacing","definedIn":"colors_and_type.css"},{"name":"--space-20","value":"80px","kind":"spacing","definedIn":"colors_and_type.css"},{"name":"--space-24","value":"96px","kind":"spacing","definedIn":"colors_and_type.css"},{"name":"--space-32","value":"128px","kind":"spacing","definedIn":"colors_and_type.css"},{"name":"--radius-2","value":"2px","kind":"radius","definedIn":"colors_and_type.css"},{"name":"--radius-4","value":"4px","kind":"radius","definedIn":"colors_and_type.css"},{"name":"--radius-6","value":"6px","kind":"radius","definedIn":"colors_and_type.css"},{"name":"--radius-8","value":"8px","kind":"radius","definedIn":"colors_and_type.css"},{"name":"--radius-10","value":"10px","kind":"radius","definedIn":"colors_and_type.css"},{"name":"--radius-12","value":"12px","kind":"radius","definedIn":"colors_and_type.css"},{"name":"--radius-16","value":"16px","kind":"radius","definedIn":"colors_and_type.css"},{"name":"--radius-20","value":"20px","kind":"radius","definedIn":"colors_and_type.css"},{"name":"--radius-24","value":"24px","kind":"radius","definedIn":"colors_and_type.css"},{"name":"--radius-32","value":"32px","kind":"radius","definedIn":"colors_and_type.css"},{"name":"--radius-pill","value":"999px","kind":"radius","definedIn":"colors_and_type.css"},{"name":"--radius-circle","value":"50%","kind":"radius","definedIn":"colors_and_type.css"},{"name":"--ease-standard","value":"cubic-bezier(0.2, 0, 0, 1)","kind":"other","definedIn":"colors_and_type.css"},{"name":"--ease-decelerate","value":"cubic-bezier(0, 0, 0, 1)","kind":"other","definedIn":"colors_and_type.css"},{"name":"--ease-accelerate","value":"cubic-bezier(0.3, 0, 1, 1)","kind":"other","definedIn":"colors_and_type.css"},{"name":"--duration-fast","value":"120ms","kind":"other","definedIn":"colors_and_type.css"},{"name":"--duration-normal","value":"200ms","kind":"other","definedIn":"colors_and_type.css"},{"name":"--duration-slow","value":"320ms","kind":"other","definedIn":"colors_and_type.css"},{"name":"--font-sans","value":"\"Pretendard JP Variable\", \"Pretendard Variable\", \"Pretendard JP\",\n                  -apple-system, BlinkMacSystemFont, \"Apple SD Gothic Neo\",\n                  \"Helvetica Neue\", \"Segoe UI\", Roboto, sans-serif","kind":"font","definedIn":"colors_and_type.css"},{"name":"--font-display","value":"\"Wanted Sans Variable\", \"Wanted Sans\", var(--font-sans)","kind":"font","definedIn":"colors_and_type.css"},{"name":"--font-mono","value":"ui-monospace, \"SF Mono\", \"JetBrains Mono\", Menlo, Consolas, monospace","kind":"font","definedIn":"colors_and_type.css"},{"name":"--type-display-1","value":"700 64px/1.20  var(--font-sans)","kind":"font","definedIn":"colors_and_type.css"},{"name":"--type-display-2","value":"700 56px/1.25  var(--font-sans)","kind":"font","definedIn":"colors_and_type.css"},{"name":"--type-title-1","value":"700 36px/1.334 var(--font-sans)","kind":"font","definedIn":"colors_and_type.css"},{"name":"--type-title-2","value":"700 32px/1.30  var(--font-sans)","kind":"font","definedIn":"colors_and_type.css"},{"name":"--type-title-3","value":"700 28px/1.358 var(--font-sans)","kind":"font","definedIn":"colors_and_type.css"},{"name":"--type-heading-1","value":"700 24px/1.334 var(--font-sans)","kind":"font","definedIn":"colors_and_type.css"},{"name":"--type-heading-2","value":"700 20px/1.40  var(--font-sans)","kind":"font","definedIn":"colors_and_type.css"},{"name":"--type-headline-1","value":"600 17px/1.412 var(--font-sans)","kind":"font","definedIn":"colors_and_type.css"},{"name":"--type-headline-2","value":"600 16px/1.50  var(--font-sans)","kind":"font","definedIn":"colors_and_type.css"},{"name":"--type-body-1-r","value":"500 16px/1.50  var(--font-sans)","kind":"font","definedIn":"colors_and_type.css"},{"name":"--type-body-1-b","value":"600 16px/1.50  var(--font-sans)","kind":"font","definedIn":"colors_and_type.css"},{"name":"--type-body-2-r","value":"500 14px/1.50  var(--font-sans)","kind":"font","definedIn":"colors_and_type.css"},{"name":"--type-body-2-b","value":"600 14px/1.50  var(--font-sans)","kind":"font","definedIn":"colors_and_type.css"},{"name":"--type-label-1","value":"600 14px/1.42  var(--font-sans)","kind":"font","definedIn":"colors_and_type.css"},{"name":"--type-label-2","value":"600 13px/1.42  var(--font-sans)","kind":"font","definedIn":"colors_and_type.css"},{"name":"--type-caption-1","value":"500 12px/1.33  var(--font-sans)","kind":"font","definedIn":"colors_and_type.css"},{"name":"--type-caption-2","value":"700 11px/1.27  var(--font-sans)","kind":"font","definedIn":"colors_and_type.css"},{"name":"--bp-sm","value":"600px","kind":"spacing","definedIn":"colors_and_type.css"},{"name":"--bp-md","value":"900px","kind":"spacing","definedIn":"colors_and_type.css"},{"name":"--bp-lg","value":"1200px","kind":"spacing","definedIn":"colors_and_type.css"},{"name":"--bp-xl","value":"1440px","kind":"spacing","definedIn":"colors_and_type.css"},{"name":"--color-label-normal","value":"rgba(247, 247, 248, 1)","kind":"color","definedIn":"colors_and_type.css","scope":"[data-theme=\"dark\"]"},{"name":"--color-label-strong","value":"#ffffff","kind":"color","definedIn":"colors_and_type.css","scope":"[data-theme=\"dark\"]"},{"name":"--color-label-neutral","value":"rgba(247, 247, 248, 0.88)","kind":"color","definedIn":"colors_and_type.css","scope":"[data-theme=\"dark\"]"},{"name":"--color-label-alternative","value":"rgba(247, 247, 248, 0.61)","kind":"color","definedIn":"colors_and_type.css","scope":"[data-theme=\"dark\"]"},{"name":"--color-label-assistive","value":"rgba(247, 247, 248, 0.28)","kind":"color","definedIn":"colors_and_type.css","scope":"[data-theme=\"dark\"]"},{"name":"--color-label-disable","value":"rgba(247, 247, 248, 0.16)","kind":"color","definedIn":"colors_and_type.css","scope":"[data-theme=\"dark\"]"},{"name":"--color-label-inverse","value":"#171719","kind":"color","definedIn":"colors_and_type.css","scope":"[data-theme=\"dark\"]"},{"name":"--color-background-normal","value":"#171719","kind":"color","definedIn":"colors_and_type.css","scope":"[data-theme=\"dark\"]"},{"name":"--color-background-alternative","value":"#1b1c1e","kind":"color","definedIn":"colors_and_type.css","scope":"[data-theme=\"dark\"]"},{"name":"--color-background-elevated","value":"#212225","kind":"color","definedIn":"colors_and_type.css","scope":"[data-theme=\"dark\"]"},{"name":"--color-background-elevated-alt","value":"#292a2d","kind":"color","definedIn":"colors_and_type.css","scope":"[data-theme=\"dark\"]"},{"name":"--color-background-inverse","value":"#ffffff","kind":"color","definedIn":"colors_and_type.css","scope":"[data-theme=\"dark\"]"},{"name":"--color-line-normal","value":"rgba(174, 176, 182, 0.22)","kind":"color","definedIn":"colors_and_type.css","scope":"[data-theme=\"dark\"]"},{"name":"--color-line-neutral","value":"rgba(174, 176, 182, 0.16)","kind":"color","definedIn":"colors_and_type.css","scope":"[data-theme=\"dark\"]"},{"name":"--color-line-alternative","value":"rgba(174, 176, 182, 0.08)","kind":"color","definedIn":"colors_and_type.css","scope":"[data-theme=\"dark\"]"},{"name":"--color-line-strong","value":"rgba(174, 176, 182, 0.40)","kind":"color","definedIn":"colors_and_type.css","scope":"[data-theme=\"dark\"]"},{"name":"--color-fill-normal","value":"rgba(174, 176, 182, 0.10)","kind":"color","definedIn":"colors_and_type.css","scope":"[data-theme=\"dark\"]"},{"name":"--color-fill-strong","value":"rgba(174, 176, 182, 0.20)","kind":"color","definedIn":"colors_and_type.css","scope":"[data-theme=\"dark\"]"},{"name":"--color-fill-neutral","value":"rgba(174, 176, 182, 0.05)","kind":"color","definedIn":"colors_and_type.css","scope":"[data-theme=\"dark\"]"},{"name":"--color-interaction-hover","value":"rgba(255, 255, 255, 0.06)","kind":"color","definedIn":"colors_and_type.css","scope":"[data-theme=\"dark\"]"},{"name":"--color-interaction-pressed","value":"rgba(255, 255, 255, 0.10)","kind":"color","definedIn":"colors_and_type.css","scope":"[data-theme=\"dark\"]"},{"name":"--color-inverse-primary","value":"var(--w-blue-50)","kind":"color","definedIn":"colors_and_type.css","scope":"[data-theme=\"dark\"]"},{"name":"--shadow-emphasize-xsmall","value":"0px 1px 2px -1px rgba(0, 0, 0, 0.40)","kind":"shadow","definedIn":"colors_and_type.css","scope":"[data-theme=\"dark\"]"},{"name":"--shadow-emphasize-small","value":"0px 1px 3px 0px  rgba(0, 0, 0, 0.50)","kind":"shadow","definedIn":"colors_and_type.css","scope":"[data-theme=\"dark\"]"},{"name":"--shadow-emphasize-medium","value":"0px 4px 8px 0px  rgba(0, 0, 0, 0.50)","kind":"shadow","definedIn":"colors_and_type.css","scope":"[data-theme=\"dark\"]"},{"name":"--shadow-emphasize-large","value":"0px 12px 24px 0px rgba(0,0,0,0.55)","kind":"shadow","definedIn":"colors_and_type.css","scope":"[data-theme=\"dark\"]"}],"themes":[{"selector":"[data-theme=\"dark\"]","label":"Dark"}],"fonts":[],"brandFonts":[{"family":"Pretendard JP Variable","status":"maybe-remote","tokens":["--font-sans"],"path":"colors_and_type.css"},{"family":"Wanted Sans Variable","status":"maybe-remote","tokens":["--font-display"],"path":"colors_and_type.css"},{"family":"JetBrains Mono","status":"maybe-remote","tokens":["--font-mono"],"path":"colors_and_type.css"}],"source":"spa"}